mat_server/__init__.py
mat_server/__main__.py
mat_server/app/__init__.py
mat_server/app/cli.py
mat_server/app/cli_test.py
mat_server/app/container.py
mat_server/app/manager.py
mat_server/app/manager_test.py
mat_server/app/server.py
mat_server/data/default/mat-data/config.yml
mat_server/data/default/mat-data/data/hello
mat_server/domain/__init__.py
mat_server/domain/base_types.py
mat_server/domain/exceptions.py
mat_server/domain/entities/__init__.py
mat_server/domain/entities/client_request.py
mat_server/domain/entities/client_request_test.py
mat_server/domain/entities/http_request.py
mat_server/domain/entities/http_request_test.py
mat_server/domain/entities/http_response.py
mat_server/domain/entities/http_response_test.py
mat_server/domain/entities/mat_config.py
mat_server/domain/entities/mat_config_test.py
mat_server/domain/entities/server_response.py
mat_server/domain/entities/server_response_test.py
mat_server/domain/entities/validation_report.py
mat_server/domain/helpers/__init__.py
mat_server/domain/helpers/data_helper.py
mat_server/domain/helpers/data_retriever_helper.py
mat_server/domain/helpers/file_helper.py
mat_server/domain/helpers/http_request_helper.py
mat_server/domain/helpers/json_helper.py
mat_server/domain/repositories/__init__.py
mat_server/domain/repositories/mat_config_repository.py
mat_server/domain/services/__init__.py
mat_server/domain/services/template_service.py
mat_server/domain/use_cases/__init__.py
mat_server/domain/use_cases/check_config_use_case.py
mat_server/domain/use_cases/check_config_use_case_test.py
mat_server/domain/use_cases/check_if_mock_response_exists_use_case.py
mat_server/domain/use_cases/check_if_mock_response_exists_use_case_test.py
mat_server/domain/use_cases/check_if_proxy_server_exists_use_case.py
mat_server/domain/use_cases/check_if_proxy_server_exists_use_case_test.py
mat_server/domain/use_cases/generate_default_config_use_case.py
mat_server/domain/use_cases/generate_default_config_use_case_test.py
mat_server-0.1.0a8.dist-info/METADATA
mat_server-0.1.0a8.dist-info/WHEEL
mat_server-0.1.0a8.dist-info/entry_points.txt
mat_server-0.1.0a8.dist-info/top_level.txt
mat_server-0.1.0a8.dist-info/RECORD
