Metadata-Version: 2.1
Name: mat-server
Version: 0.1.0a8
Summary: mat server 代理伺服器
Home-page: https://github.com/marco79423/mat-server
Author: 兩大類
Author-email: marco79423@gmail.com
License: UNKNOWN
Platform: UNKNOWN
Classifier: Programming Language :: Python :: 3.6
Classifier: Programming Language :: Python :: 3.7
Classifier: Programming Language :: Python :: 3.8
Classifier: Programming Language :: Python :: 3.9
Requires-Python: >=3.6
Requires-Dist: dependency-injector (==3.44.0)
Requires-Dist: aiostream (==0.4.1)
Requires-Dist: click (==7.1.2)
Requires-Dist: fastapi (==0.61.2)
Requires-Dist: uvicorn (==0.12.2)
Requires-Dist: requests (==2.24.0)
Requires-Dist: PyYAML (==5.3.1)
Requires-Dist: lark-parser[regex]
Requires-Dist: pymongo (==3.11.0)
